aquasec/__init__.py
aquasec/auth.py
aquasec/code_repositories.py
aquasec/common.py
aquasec/config.py
aquasec/enforcers.py
aquasec/functions.py
aquasec/inventory.py
aquasec/licenses.py
aquasec/repositories.py
aquasec/scopes.py
aquasec/vms.py
aquasec-0.7.2.dist-info/licenses/LICENSE
aquasec-0.7.2.dist-info/METADATA
aquasec-0.7.2.dist-info/WHEEL
aquasec-0.7.2.dist-info/top_level.txt
aquasec-0.7.2.dist-info/RECORD
