Metadata-Version: 2.4
Name: aquasec
Version: 0.7.2
Summary: API client library for Aqua Security platform
Home-page: https://github.com/andreazorzetto/aquasec-lib
Author: Andrea Zorzetto
Classifier: Programming Language :: Python :: 3
Classifier: License :: OSI Approved :: MIT License
Classifier: Operating System :: OS Independent
Classifier: Development Status :: 4 - Beta
Classifier: Intended Audience :: Developers
Classifier: Topic :: Software Development :: Libraries :: Python Modules
Requires-Python: >=3.7
License-File: LICENSE
Requires-Dist: requests>=2.28.0
Requires-Dist: prettytable>=3.5.0
Requires-Dist: cryptography>=41.0.0
Requires-Dist: inquirer>=3.1.0
Dynamic: author
Dynamic: classifier
Dynamic: description
Dynamic: description-content-type
Dynamic: home-page
Dynamic: license-file
Dynamic: requires-dist
Dynamic: requires-python
Dynamic: summary
